data_tools/__init__.py
data_tools/connection/__init__.py
data_tools/connection/mongodb/__init__.py
data_tools/connection/mongodb/api.py
data_tools/connection/mysql/__init__.py
data_tools/connection/mysql/api.py
data_tools/tools/__init__.py
data_tools/tools/api.py
data_tools_traders_club-0.1.0.dist-info/AUTHORS.rst
data_tools_traders_club-0.1.0.dist-info/LICENSE
data_tools_traders_club-0.1.0.dist-info/METADATA
data_tools_traders_club-0.1.0.dist-info/WHEEL
data_tools_traders_club-0.1.0.dist-info/top_level.txt
data_tools_traders_club-0.1.0.dist-info/RECORD
