Metadata-Version: 2.1
Name: data-tools-traders-club
Version: 0.1.0
Summary: Data science oriented tools package
Home-page: UNKNOWN
Author: Fabio Caffarello
Author-email: fabio.caffarello@tc.com.br
License: UNKNOWN
Platform: UNKNOWN
Requires-Python: >=3.6
Requires-Dist: pandas (>=1.2)
Requires-Dist: SQLAlchemy (>=1.4)
Requires-Dist: dnspython (>=2.1)
Requires-Dist: pymongo (>=3.11)
Requires-Dist: PyMySQL (>=1.0)
Requires-Dist: inflection (>=0.5)
Requires-Dist: py-make (>=0.1)
Requires-Dist: python-dotenv (>=0.17)
Requires-Dist: Pyment (>=0.3)
